README.md
setup.cfg
setup.py
remote_config/__init__.py
remote_config/base.py
remote_config/validator.py
remote_config.egg-info/PKG-INFO
remote_config.egg-info/SOURCES.txt
remote_config.egg-info/dependency_links.txt
remote_config.egg-info/not-zip-safe
remote_config.egg-info/requires.txt
remote_config.egg-info/top_level.txt
test/__init__.py
test/mock_data.py
test/test_base.py