Metadata-Version: 2.1
Name: remote-config
Version: 0.1.7
Summary: Remote config and feature toggle based on Consul.
Home-page: https://github.com/lojaintegrada/remote-config
Author: Loja Integrada
Author-email: suporte@lojaintegrada.com.br
License: MIT
Platform: UNKNOWN
Classifier: Development Status :: 3 - Alpha
Classifier: Environment :: Web Environment
Classifier: Intended Audience :: Developers
Classifier: License :: OSI Approved :: MIT License
Classifier: Operating System :: OS Independent
Classifier: Programming Language :: Python
Classifier: Programming Language :: Python :: 2.7
Classifier: Topic :: Software Development :: Libraries :: Python Modules
Classifier: Topic :: Internet
